cartogeo/__init__.py
cartogeo/coord.py
cartogeo/helper.py
cartogeo/exceptions/__init__.py
cartogeo/exceptions/invalid_coord_exception.py
cartogeo/exceptions/invalid_sheet_exception.py
cartogeo/map/__init__.py
cartogeo/map/__main__.py
cartogeo/map/map.py
cartogeo/map/map_250k.py
cartogeo/map/map_25_or_50k.py
cartogeo/map/map_25k.py
cartogeo/map/map_50k.py
cartogeo/map/map_miniscale.py
cartogeo/pdf/__init__.py
cartogeo/pdf/__main__.py
cartogeo/pdf/page_orientation.py
cartogeo/pdf/pdf.py
cartogeo/test/__init__.py
cartogeo/test/__main__.py
tests/__init__.py
tests/test_coord.py
tests/map/__init__.py
tests/map/test_map_50k.py
cartogeo_generator-0.0.3.dist-info/METADATA
cartogeo_generator-0.0.3.dist-info/WHEEL
cartogeo_generator-0.0.3.dist-info/top_level.txt
cartogeo_generator-0.0.3.dist-info/RECORD
