Metadata-Version: 2.1
Name: cartogeo-generator
Version: 0.0.3
Summary: Tool to generate maps
Home-page: https://bitbucket.org/davidksouthgate/
Author: David Southgate
Author-email: d@davidsouthgate.co.uk
License: UNKNOWN
Platform: UNKNOWN
Classifier: Programming Language :: Python :: 3
Classifier: Operating System :: OS Independent
Requires-Dist: numpy (==1.16.*)
Requires-Dist: pillow (==6.*)
Requires-Dist: scikit-image (==0.15.*)
Requires-Dist: fpdf
Requires-Dist: mock
Requires-Dist: toml
Requires-Dist: twine
